README.rst
allocator.py
setup.py
resource_allocator.egg-info/PKG-INFO
resource_allocator.egg-info/SOURCES.txt
resource_allocator.egg-info/dependency_links.txt
resource_allocator.egg-info/requires.txt
resource_allocator.egg-info/top_level.txt