Metadata-Version: 1.1
Name: resource-allocator
Version: 0.1.0
Summary: Python Resource Allocation API
Home-page: https://github.com/javicacheiro/resource-allocation
Author: Jonatan Enes & Javier Cacheiro
Author-email: bigdata-dev@listas.cesga.es
License: MIT
Platform: UNKNOWN
Classifier: License :: OSI Approved :: MIT License
Classifier: Intended Audience :: Developers
Classifier: Intended Audience :: System Administrators
Classifier: Operating System :: OS Independent
Classifier: Topic :: Software Development :: Libraries :: Python Modules
